boolean_parser/__init__.py
boolean_parser/clauses.py
boolean_parser/actions/__init__.py
boolean_parser/actions/boolean.py
boolean_parser/actions/clause.py
boolean_parser/mixins/__init__.py
boolean_parser/mixins/sqla.py
boolean_parser/parsers/__init__.py
boolean_parser/parsers/base.py
boolean_parser/parsers/sqla.py
tests/__init__.py
tests/conftest.py
tests/database.py
tests/models.py
tests/test_clauses.py
tests/test_parse.py
boolean_parser-0.1.4.dist-info/LICENSE.md
boolean_parser-0.1.4.dist-info/METADATA
boolean_parser-0.1.4.dist-info/WHEEL
boolean_parser-0.1.4.dist-info/top_level.txt
boolean_parser-0.1.4.dist-info/RECORD
