Metadata-Version: 2.1
Name: boolean-parser
Version: 0.1.4
Summary: Package for parsing strings containing conditional boolean logic
Home-page: https://github.com/havok2063/boolean_parser
Author: Brian Cherinka
Author-email: havok2063@gmail.com
License: BSD 3-Clause License
Project-URL: Repository, https://github.com/havok2063/boolean_parser
Project-URL: Documentation, https://boolean-parser.readthedocs.org
Keywords: software,parsing,sqlalchemy
Platform: UNKNOWN
Classifier: Development Status :: 4 - Beta
Classifier: Intended Audience :: Science/Research
Classifier: Natural Language :: English
Classifier: Operating System :: OS Independent
Classifier: Programming Language :: Python
Classifier: Programming Language :: Python :: 3.6
Classifier: Programming Language :: Python :: 3.7
Classifier: Topic :: Documentation :: Sphinx
Classifier: Topic :: Software Development :: Libraries :: Python Modules
Requires-Python: >=3.6
Requires-Dist: six (>=1.16.0)
Requires-Dist: pyparsing (>=2.4)
Requires-Dist: sqlalchemy (>=1.4.0)
Provides-Extra: dev
Requires-Dist: pytest (>=5.4) ; extra == 'dev'
Requires-Dist: pytest-cov (>=2.4.0) ; extra == 'dev'
Requires-Dist: pytest-sugar (>=0.8.0) ; extra == 'dev'
Requires-Dist: ipython (>=7.13.0) ; extra == 'dev'
Requires-Dist: factory-boy (>=2.12.0) ; extra == 'dev'
Requires-Dist: pytest-factoryboy (>=2.0.3) ; extra == 'dev'
Provides-Extra: docs
Requires-Dist: Sphinx (>=1.8.0) ; extra == 'docs'
Requires-Dist: sphinx-bootstrap-theme (>=0.4.12) ; extra == 'docs'
Requires-Dist: sphinx-issues (>=1.2.0) ; extra == 'docs'
Requires-Dist: Jinja2 (<3.1) ; extra == 'docs'
